evernote_mcp/__init__.py
evernote_mcp/__main__.py
evernote_mcp/client.py
evernote_mcp/config.py
evernote_mcp/resources/__init__.py
evernote_mcp/resources/note_resource.py
evernote_mcp/resources/notebook_resource.py
evernote_mcp/tools/__init__.py
evernote_mcp/tools/note_tools.py
evernote_mcp/tools/notebook_tools.py
evernote_mcp/tools/search_tools.py
evernote_mcp/util/__init__.py
evernote_mcp/util/enml_converter.py
evernote_mcp/util/error_handler.py
evernote_mcp-0.1.2.dist-info/METADATA
evernote_mcp-0.1.2.dist-info/WHEEL
evernote_mcp-0.1.2.dist-info/entry_points.txt
evernote_mcp-0.1.2.dist-info/RECORD
