Metadata-Version: 2.4
Name: evernote-mcp
Version: 0.1.2
Summary: Model Context Protocol (MCP) server for Evernote operations
License-Expression: MIT
Keywords: evernote,mcp,model-context-protocol,ai,claude
Author: king
Author-email: king@example.com
Requires-Python: >=3.10,<4.0
Classifier: License :: OSI Approved :: MIT License
Classifier: Programming Language :: Python :: 3
Classifier: Programming Language :: Python :: 3.10
Classifier: Programming Language :: Python :: 3.11
Classifier: Programming Language :: Python :: 3.12
Classifier: Development Status :: 4 - Beta
Requires-Dist: evernote-backup (>=1.0.0)
Requires-Dist: mcp (>=0.1.0)
Requires-Dist: python-dotenv (>=1.0.0)
Project-URL: Repository, https://github.com/king/evernote-mcp
